Workbook

Sheet Leia-me
A1: Fact check das premissas do revenue build · Intelbras (INTB3)
A3: Objetivo | B3: Testar, com fórmulas, se as premissas propostas para a receita fecham com o que a Intelbras reportou.
A4: Como ler | B4: Aba 'Fact check': cada linha é um teste. Resultado = o que a premissa implica; Referência = o dado real; Desvio = diferença.
B5: Aba 'Teste 2036': o que acontece quando as premissas são compostas por 11 anos.
B6: Aba 'Dados': todos os números usados, com fonte. Mude ali e as outras abas recalculam.
A7: Cores | B7: Azul = dado digitado (com fonte) · Preto = fórmula · Verde = vínculo com outra aba · Fundo amarelo = premissa do usuário ou hipótese própria.
A8: Veredito | B8: Vermelho = reprovada (não fecha com os dados) · Amarelo = ajustar · Verde = ok.
A9: Unidades | B9: R$ mi, salvo indicação. Percentuais guardados como fração. 'p.p.' = pontos percentuais.

Sheet Dados
A1: Dados e premissas (R$ mi, salvo indicação)
A3: 1. Premissas propostas
A4: Mercado MIDI (2026) | B4: 7200 | C4: R$ mi | D4: Premissa do usuário
A5: Share de Segurança (premissa) | B5: 0.62 | C5: % | D5: Premissa do usuário ('estável em 62% do share')
A6: Solar como % da receita de Energia | B6: 0.5 | C6: % | D6: Premissa do usuário
A7: Share solar constante | B7: 0.018 | C7: % | D7: Premissa do usuário
A10: 2. Receita líquida por BU (R$ mi)
A11: BU | B11: 2023 | C11: 2024 | D11: 2025 | E11: 1S25 | F11: 1S26 | G11: LTM 2T26
A12: Segurança | B12: 2225.2 | C12: 2602.7 | D12: 2730.3 | E12: 1305.2 | F12: 1380.9 | G12: =D12-E12+F12 -> 2806
A13: TIC | B13: 907.9 | C13: 1062.2 | D13: 977.2 | E13: 470.8 | F13: 535.4 | G13: =D13-E13+F13 -> 1041.8
A14: Energia | B14: 970.5 | C14: 1091.2 | D14: 752.9 | E14: 391.8 | F14: 343.4 | G14: =D14-E14+F14 -> 704.5
A15: Total | B15: =SUM(B12:B14) -> 4103.6 | C15: =SUM(C12:C14) -> 4756.1 | D15: =SUM(D12:D14) -> 4460.4 | E15: =SUM(E12:E14) -> 2167.8 | F15: =SUM(F12:F14) -> 2259.7 | G15: =SUM(G12:G14) -> 4552.3
A16: Fonte: planilha de RI 2T26 (aba Informações por Segmento), soma dos trimestres. LTM 2T26 = 2025 − 1S25 + 1S26.
A18: 3. Demais dados
A19: Item | B19: Valor | C19: Unidade | D19: Fonte
A20: Share MIDI Segurança 2024 | B20: 0.43 | C20: % | D20: FRE 2026, item 1.1 (controladora)
A21: Share MIDI Segurança 2025 | B21: 0.44 | C21: % | D21: FRE 2026, item 1.1 ('mais de 44%')
A22: Share MIDI TIC 2025 | B22: 0.09 | C22: % | D22: FRE 2026, item 1.1
A23: Share MIDI Energia ex-solar 2025 | B23: 0.19 | C23: % | D23: FRE 2026, item 1.1
A24: Share solar 2025 | B24: 0.019 | C24: % | D24: FRE 2026, item 1.4
A25: Share solar 1S26 | B25: 0.017 | C25: % | D25: Case, slide 22 (MW de GD por marca do inversor)
A26: Share solar 2020 | B26: 0.085 | C26: % | D26: Case, slide 22
A27: Receita bruta consolidada 2025 | B27: 5658.5 | C27: R$ mi | D27: DFP 2025, NE 26
A28: Receita líquida consolidada 2025 | B28: 4460.4 | C28: R$ mi | D28: DFP 2025, NE 26
A29: Receita bruta consolidada 2024 | B29: 6016.9 | C29: R$ mi | D29: DFP 2025, NE 26
A30: Receita líquida consolidada 2024 | B30: 4756.1 | C30: R$ mi | D30: DFP 2025, NE 26
A31: Abese: faturamento do setor 2018 | B31: 6.25 | C31: R$ bi | D31: Case, slide 19 (Abese)
... A50: XP: crescimento da receita em 2026 | B50: 0.005 | C50: % | D50: XP, prévia 1T26

Sheet Fact check
A1: Fact check das premissas
A2: Resultado = o que a premissa implica · Referência = dado reportado ou fonte externa · Desvio = Resultado vs Referência
A4: # | B4: Premissa | C4: Teste | D4: Resultado | E4: Referência | F4: Desvio | G4: Veredito | H4: O que fazer
A5: Mercado (R$ 7,2 bi do MIDI)
A6: 1 | B6: Mercado de R$7,2 bi dividido entre as 3 BUs | C6: Só o mercado de TIC implícito no MIDI (receita ÷ share) cabe em R$7,2 bi? | D6: =Dados!$D$13/Dados!$B$22 -> 10857.778 | E6: =Dados!$B$4 -> 7200 | F6: =IFERROR(D6/E6-1,0) -> 0.50802469 | G6: Reprovada | H6: Os R$7,2 bi são só Segurança (slide 20: vídeo, alarmes e acesso). Cada BU precisa do seu mercado.
A7: Segurança
A8: 2 | B8: Share de 62%, leitura A: market share | C8: 7,2 bi × 62% = receita de Segurança de 2025? | D8: =Dados!$B$4*Dados!$B$5 -> 4464 | E8: =Dados!$D$12 -> 2730.3 | F8: =IFERROR(D8/E8-1,0) -> 0.63498517 | G8: Reprovada | H8: 62% × 7,2 bi = R$4,46 bi, a receita da Intelbras inteira em 2025.
A9: 3 | B9: Share de 62%, leitura B: 62% do mercado é Segurança | C9: 7,2 bi × 62% × share de 44% = receita de Segurança? | D9: =Dados!$B$4*Dados!$B$5*Dados!$B$21 -> 1964.16 | E9: =Dados!$D$12 -> 2730.3 | F9: =IFERROR(D9/E9-1,0) -> -0.28060653 | G9: Reprovada | H9: Também não fecha: fica 28% abaixo.
A10: 4 | B10: O que é o 62%? | C10: Peso de Segurança na receita (LTM 2T26) vs market share do FRE | D10: =Dados!$G$12/Dados!$G$15 -> 0.61639171 | E10: =Dados!$B$21 -> 0.44 | F10: =(D10-E10)*100 -> 17.639171 | G10: Reprovada | H10: 62% é o peso da BU na receita da Intelbras, não market share. O share do FRE é 44%.
A11: 5 | B11: Share do FRE (44%) sobre os 7,2 bi | C11: 7,2 bi × 44% vs receita líquida de Segurança 2025 | D11: =Dados!$B$4*Dados!$B$21 -> 3168 | E11: =Dados!$D$12 -> 2730.3 | F11: =IFERROR(D11/E11-1,0) -> 0.16031205 | G11: Ajustar | H11: Não fecha na receita líquida. Os 7,2 bi e os 44% têm definições diferentes.
A12: 6 | B12: Share do FRE (44%) sobre os 7,2 bi | C12: 7,2 bi × 44% vs receita bruta estimada de Segurança (líquida × bruta/líquida consolidada) | D12: =Dados!$B$4*Dados!$B$21 -> 3168 | E12: =Dados!$D$12*Dados!$B$27/Dados!$B$28 -> 3463.681 | F12: =IFERROR(D12/E12-1,0) -> -0.085366107 | G12: Ajustar | H12: Também não fecha na bruta. Solução: share calibrado ou método de índice (linha abaixo).
A13: 7 | B13: Share calibrado, se usar os 7,2 bi | C13: Receita de Segurança LTM 2T26 ÷ 7,2 bi | D13: =Dados!$G$12/Dados!$B$4 -> 0.38972222 | E13: =Dados!$B$21 -> 0.44 | F13: =(D13-E13)*100 -> -5.0277778 | G13: Ajustar | H13: Use ~39% como share calibrado ou projete Receita(t) = Receita(2025) × Mercado(t)/Mercado(2025) × Share(t)/Share(2025).
A14: 8 | B14: Crescimento pela Abese: 2024 | C14: Crescimento do setor (Abese) vs receita de Segurança da Intelbras | D14: =Dados!$B$33 -> 0.161 | E14: =Dados!$C$12/Dados!$B$12-1 -> 0.16964767 | F14: =(D14-E14)*100 -> -0.86476721 | G14: OK | H14: Bateu em 2024, ano de recomposição de estoque após a seca de 2023.
A15: 9 | B15: Crescimento pela Abese: 2025 | C15: Abese 2025 vs Segurança 2025 (o share MIDI ficou estável, 43% → 44%) | D15: =Dados!$B$34/Dados!$B$32-1 -> 0.14285714 | E15: =Dados!$D$12/Dados!$C$12-1 -> 0.049026011 | F15: =(D15-E15)*100 -> 9.3831131 | G15: Reprovada | H15: A Abese inclui serviços (monitoramento, portaria remota +24%, software +22%). O mercado de equipamentos cresceu ~2,5%.
A16: 10 | B16: Crescimento pela Abese: 2026 | C16: Abese 2026E vs Segurança no 1S26 | D16: =Dados!$B$35/Dados!$B$34-1 -> 0.1875 | E16: =Dados!$F$12/Dados!$E$12-1 -> 0.057998774 | F16: =(D16-E16)*100 -> 12.950123 | G16: Reprovada | H16: A diferença aumenta. O release diz que o 1S26 'reflete o mercado em geral' (+5,8%).
A17: 11 | B17: Backtest: Abese com share estável | C17: Segurança 2024 × (1 + Abese 2025) vs Segurança 2025 real | D17: =Dados!$C$12*Dados!$B$34/Dados!$B$32 -> 2974.5143 | E17: =Dados!$D$12 -> 2730.3 | F17: =IFERROR(D17/E17-1,0) -> 0.089445953 | G17: Reprovada | H17: A premissa teria errado 2025 em ~9% para cima já no primeiro ano.
A18: 12 | B18: Abese composta até 2036 | C18: Segurança 2036 com o CAGR da Abese 2018–25 vs com o PIB nominal de longo prazo | D18: =Dados!$D$12*(1+((Dados!$B$34/Dados!$B$31)^(1/7)-1))^Dados!$B$48 -> 11959.976 | E18: =Dados!$D$12*((1+Dados!$B$46)*(1+Dados!$B$47))^Dados!$B$48 -> 4956.2831 | F18: =IFERROR(D18/E18-1,0) -> 1.4130938 | G18: Reprovada | H18: Segurança chegaria a ~R$12 bi, 1,7x o mercado de hoje. Não converge para o g da perpetuidade (ver 'Teste 2036').
A19: Energia: solar
A20: 13 | B20: Solar = 50% da receita de Energia | C20: Preço por watt implícito: (Energia 2025 × 50%) ÷ (GD 2025 × share 1,9%) vs preço do kit | D20: =(Dados!$D$14*Dados!$B$6)/(Dados!$B$36*1000*Dados!$B$24) -> 2.5401484 | E20: =Dados!$B$37*Dados!$B$39 -> 1.746 | F20: =IFERROR(D20/E20-1,0) -> 0.45483874 | G20: Reprovada | H20: 50% exigiria vender o kit a ~R$2,54/W, acima do sistema comercial instalado (R$2,02). Implausível.
A21: 14 | B21: Solar = 50% da receita de Energia | C21: Peso de solar implícito pelo preço do kit: GD × share × R$/W ÷ Energia 2025 | D21: =(Dados!$B$36*1000*Dados!$B$24*Dados!$B$37*Dados!$B$39)/Dados!$D$14 -> 0.3436807 | E21: =Dados!$B$6 -> 0.5 | F21: =(D21-E21)*100 -> -15.63193 | G21: Ajustar | H21: Solar seria ~1/3 em 2025 e menos em 2026 (nobreaks e carregadores crescendo; solar no 'novo patamar').
A22: 15 | B22: Share solar constante em 1,8% | C22: Premissa vs último dado (1S26) | D22: =Dados!$B$7 -> 0.018 | E22: =Dados!$B$25 -> 0.017 | F22: =(D22-E22)*100 -> 0.1 | G22: Ajustar | H22: A premissa já parte acima do dado atual.
A23: 16 | B23: Share solar constante em 1,8% | C23: Tendência: variação anual do share 2020–25 vs premissa de 0% | D23: =(Dados!$B$24/Dados!$B$26)^(1/5)-1 -> -0.25891686 | E23: =0 -> 0 | F23: =(D23-E23)*100 -> -25.891686 | G23: Reprovada | H23: O share cai ~26% ao ano, e a empresa despriorizou solar desde o 3T25. No mínimo, deixe-o cair até um piso.
A24: 17 | B24: Crescimento pela Absolar (GW) | C24: Variação anual do preço por watt (jan/17 → 2026) vs crescimento em GW | D24: =(Dados!$B$37/Dados!$B$40)^(1/Dados!$B$41)-1 -> -0.10963573 | E24: =0 -> 0 | F24: =(D24-E24)*100 -> -10.963573 | G24: Ajustar | H24: Receita em R$ = GW × share × R$/W. Crescer pela Absolar em GW sem o preço superestima a receita.
A25: 18 | B25: Perímetro do share solar | C25: O 1,9% é medido sobre toda a GD (micro + mini). A premissa usa só microgeração on-grid. | D25: — | E25: — | F25: — | G25: Ajustar | H25: Share e mercado no mesmo perímetro: recalcule o share só sobre a micro, ou use a GD total.
A26: Energia: sem solar
A27: 19 | B27: Outros 50% = nobreaks + carregadores | C27: A divisão cobre o portfólio do FRE? | D27: — | E27: — | F27: — | G27: Ajustar | H27: Faltam fontes de alimentação (CFTV) e baterias/proteção (FRE 1.4: itens xiv e xv). Use o share MIDI de 19% de Energia ex-solar.
A28: 20 | B28: Carregadores pela frota de VE | C28: Frota eletrificada em 2036 crescendo 64% a.a. vs frota total de automóveis | D28: =Dados!$B$42*(1+Dados!$B$43)^Dados!$B$48 -> 141495.56 | E28: =Dados!$B$44 -> 63300 | F28: =IFERROR(D28/E28-1,0) -> 1.2353169 | G28: Reprovada | H28: Daria mais veículos elétricos que automóveis no país. Use curva de penetração (% das vendas), com teto.
A29: TIC
A30: 21 | B30: TIC cresce com o setor de fibra | C30: 2025: TIC vs acessos de banda larga | D30: =Dados!$D$13/Dados!$C$13-1 -> -0.080022595 | E30: =Dados!$B$45 -> 0.027 | F30: =(D30-E30)*100 -> -10.702259 | G30: Reprovada | H30: A TIC caiu 8% com o setor crescendo: a Intelbras reduziu GPON de propósito.
A31: 22 | B31: TIC cresce com o setor de fibra | C31: 1S26: TIC vs acessos de banda larga | D31: =Dados!$F$13/Dados!$E$13-1 -> 0.13721325 | E31: =Dados!$B$45 -> 0.027 | F31: =(D31-E31)*100 -> 11.021325 | G31: Reprovada | H31: Agora a TIC sobe 13,7%: antidumping em cabos (fábrica no limite) e redes empresariais. O setor de fibra não explica nenhum dos dois anos.
A32: Receita bruta e total
A33: 23 | B33: Projetar receita bruta | C33: Receita bruta ÷ líquida consolidada 2025 vs 2024 | D33: =Dados!$B$27/Dados!$B$28 -> 1.2686082 | E33: =Dados!$B$29/Dados!$B$30 -> 1.2650911 | F33: =IFERROR(D33/E33-1,0) -> 0.0027800767 | G33: Ajustar | H33: Os segmentos só divulgam receita líquida, e a reforma tributária (2027–33) e o fim do ICMS incentivado mudam as deduções. Projete a líquida.
A34: 24 | B34: Total 2026E com as premissas literais | C34: Segurança (7,2 bi × 62%) + TIC 2025 × (1 + banda larga) + Energia LTM vs receita total de 2025 | D34: =Dados!$B$4*Dados!$B$5+Dados!$D$13*(1+Dados!$B$45)+Dados!$G$14 -> 6172.0844 | E34: =Dados!$D$15 -> 4460.4 | F34: =IFERROR(D34/E34-1,0) -> 0.38375132 | G34: Reprovada | H34: Salto de ~38% no primeiro ano. O 1S26 cresceu 4,2%; JP Morgan vê +3,1% no 2S26; XP, +0,5% em 2026.
A36: Resumo
B37: Reprovadas | D37: =COUNTIF(G5:G34,"Reprovada") -> 14
B38: Ajustar | D38: =COUNTIF(G5:G34,"Ajustar") -> 9
B39: OK | D39: =COUNTIF(G5:G34,"OK") -> 1

Sheet Teste 2036
A1: Teste 2036: as premissas compostas por 11 anos (R$ mi)
A2: Não são cases: mostra só o que cada taxa de crescimento implica no ano terminal.
A4: Taxas
A5: CAGR da Abese 2018–25 | B5: =(Dados!$B$34/Dados!$B$31)^(1/7)-1 -> 0.14372074
A6: Crescimento da Abese 2026E | B6: =Dados!$B$35/Dados!$B$34-1 -> 0.1875
A7: PIB nominal de longo prazo (Focus 2029) | B7: =(1+Dados!$B$46)*(1+Dados!$B$47)-1 -> 0.0557
A8: Mercado MIDI implícito 2025 (receita × share 2024/2025) | B8: =Dados!$D$12/Dados!$C$12*Dados!$B$20/Dados!$B$21-1 -> 0.025184511
A9: Frota eletrificada (2025) | B9: =Dados!$B$43 -> 0.64
A11: Linha | B11: 2025 | C11: 2026E | D11: 2027E | E11: 2028E | F11: 2029E | G11: 2030E | H11: 2031E | I11: 2032E | J11: 2033E | K11: 2034E | L11: 2035E | M11: 2036E | N11: 2036 ÷ 2025
A12: Segurança: Abese (CAGR 2018–25) | B12: =Dados!$D$12 -> 2730.3 | C12: =B12*(1+$B$5) -> 3122.7007 | D12: =C12*(1+$B$5) -> 3571.4976 | E12: =D12*(1+$B$5) -> 4084.7958 | F12: =E12*(1+$B$5) -> 4671.8657 | G12: =F12*(1+$B$5) -> 5343.3097 | H12: =G12*(1+$B$5) -> 6111.2541 | I12: =H12*(1+$B$5) -> 6989.568 | J12: =I12*(1+$B$5) -> 7994.1139 | ... M12: =L12*(1+$B$5) -> 11959.976 | N12: =M12/B12 -> 4.3804623
A13: Segurança: premissa literal (7,2 bi × 62% em 2026, depois Abese) | B13: — | C13: =Dados!$B$4*Dados!$B$5 -> 4464 | D13: =C13*(1+$B$5) -> 5105.5694 | E13: =D13*(1+$B$5) -> 5839.3456 | F13: =E13*(1+$B$5) -> 6678.5806 | G13: =F13*(1+$B$5) -> 7638.4311 | H13: =G13*(1+$B$5) -> 8736.232 | I13: =H13*(1+$B$5) -> 9991.8097 | J13: =I13*(1+$B$5) -> 11427.84 | K13: =J13*(1+$B$5) -> 13070.258 | ... M13: =L13*(1+$B$5) -> 17097.166 | N13: =M13/Dados!$D$12 -> 6.2620102
A14: Segurança: PIB nominal de longo prazo | B14: =Dados!$D$12 -> 2730.3 | C14: =B14*(1+$B$7) -> 2882.3777 | D14: =C14*(1+$B$7) -> 3042.9261 | E14: =D14*(1+$B$7) -> 3212.4171 | F14: =E14*(1+$B$7) -> 3391.3488 | G14: =F14*(1+$B$7) -> 3580.2469 | H14: =G14*(1+$B$7) -> 3779.6666 | I14: =H14*(1+$B$7) -> 3990.1941 | J14: =I14*(1+$B$7) -> 4212.4479 | ... M14: =L14*(1+$B$7) -> 4956.2831 | N14: =M14/B14 -> 1.8152888
A15: Segurança: mercado MIDI implícito de 2025 | B15: =Dados!$D$12 -> 2730.3 | C15: =B15*(1+$B$8) -> 2799.0613 | D15: =C15*(1+$B$8) -> 2869.5543 | E15: =D15*(1+$B$8) -> 2941.8226 | F15: =E15*(1+$B$8) -> 3015.9109 | G15: =F15*(1+$B$8) -> 3091.8652 | H15: =G15*(1+$B$8) -> 3169.7323 | I15: =H15*(1+$B$8) -> 3249.5605 | J15: =I15*(1+$B$8) -> 3331.3991 | ... M15: =L15*(1+$B$8) -> 3589.4902 | N15: =M15/B15 -> 1.3146871
A16: Frota eletrificada (mil) a +64% a.a. | B16: =Dados!$B$42 -> 613 | C16: =B16*(1+$B$9) -> 1005.32 | D16: =C16*(1+$B$9) -> 1648.7248 | E16: =D16*(1+$B$9) -> 2703.9087 | F16: =E16*(1+$B$9) -> 4434.4102 | G16: =F16*(1+$B$9) -> 7272.4328 | H16: =G16*(1+$B$9) -> 11926.79 | I16: =H16*(1+$B$9) -> 19559.935 | J16: =I16*(1+$B$9) -> 32078.294 | ... M16: =L16*(1+$B$9) -> 141495.56 | N16: =M16/B16 -> 230.82473
A18: Referências
A19: Mercado de Segurança hoje (premissa de 7,2 bi) | M19: =Dados!$B$4 -> 7200
A20: Receita total da Intelbras em 2025 | M20: =Dados!$D$15 -> 4460.4
A21: Frota de automóveis no Brasil (mil, 2024) | M21: =Dados!$B$44 -> 63300
A23: Leitura: com a Abese, Segurança sozinha chegaria a ~1,7x o mercado de hoje; pela premissa literal, quase 4x a receita atual da empresa. A frota elétrica passaria a frota total de automóveis. Taxas de curto prazo não podem ser compostas por 11 anos: use o fade até o g da perpetuidade.
